lunarsky/__init__.py
lunarsky/mcmf.py
lunarsky/moon.py
lunarsky/sky_coordinate.py
lunarsky/spice_utils.py
lunarsky/time.py
lunarsky/topo.py
lunarsky/version.py
lunarsky/data/__init__.py
lunarsky/data/fk/satellites/moon_080317.tf
lunarsky/data/fk/satellites/moon_assoc_me.tf
lunarsky/data/pck/moon_pa_de421_1900-2050.bpc
lunarsky/tests/conftest.py
lunarsky/tests/test_moon.py
lunarsky/tests/test_sky_coordinate.py
lunarsky/tests/test_spice.py
lunarsky/tests/test_time.py
lunarsky/tests/test_transforms.py
lunarsky-0.2.6.dist-info/LICENSE
lunarsky-0.2.6.dist-info/METADATA
lunarsky-0.2.6.dist-info/WHEEL
lunarsky-0.2.6.dist-info/top_level.txt
lunarsky-0.2.6.dist-info/RECORD
