Metadata-Version: 2.1
Name: lunarsky
Version: 0.2.6
Summary: Astropy support for selenocentric (Moon)reference frames and lunar surface observatories.
Home-page: https://github.com/aelanman/lunarsky
Download-URL: https://github.com/aelanman/lunarsky/archive/refs/tags/v0.1.1.tar.gz
Author: Adam E. Lanman
License: BSD
Keywords: astronomy moon spice
Classifier: Development Status :: 3 - Alpha
Classifier: Intended Audience :: Science/Research
Classifier: License :: OSI Approved :: BSD License
Classifier: Programming Language :: Python :: 3.6
Classifier: Topic :: Scientific/Engineering :: Astronomy
License-File: LICENSE
Requires-Dist: numpy >=1.15
Requires-Dist: astropy >=6.0.0
Requires-Dist: spiceypy
Requires-Dist: jplephem
